{"version":"0.4","title":"Section: Press Listing: Default","type":"section","content":[{"id":"61c17b80","settings":[],"elements":[{"id":"15f0367b","settings":{"_column_size":100,"_inline_size":null,"space_between_widgets":36},"elements":[{"id":"3fe8c15a","settings":{"css_classes":"press-listing","html_tag":"article","background_background":"classic","border_border":"solid","border_width":{"unit":"px","top":"1","right":"1","bottom":"1","left":"1","isLinked":true},"border_color":"#D5D5D4","padding":{"unit":"em","top":"0.5","right":"0.5","bottom":"0.5","left":"0.5","isLinked":true}},"elements":[{"id":"1199e8f8","settings":{"_column_size":100,"_inline_size":null,"_inline_size_tablet":88,"_inline_size_mobile":80},"elements":[{"id":"c5e2352","settings":{"title":"Press Article Title","link":{"url":"#","is_external":"on","nofollow":""},"header_size":"h3","typography_font_size":{"unit":"em","size":1.25,"sizes":[]},"eael_tooltip_section_content":"I am a tooltip","eael_ext_content_protection_password_placeholder":"Enter Password","eael_ext_content_protection_password_submit_btn_txt":"Submit"},"elements":[],"isInner":false,"widgetType":"heading","elType":"widget"},{"id":"56d783e9","settings":{"editor":"<p><em>Media Outlet<\/em>, Publication Date<\/p>","typography_font_size":{"unit":"em","size":0.770000000000000017763568394002504646778106689453125,"sizes":[]},"eael_tooltip_section_content":"I am a tooltip","eael_ext_content_protection_password_placeholder":"Enter Password","eael_ext_content_protection_password_submit_btn_txt":"Submit"},"elements":[],"isInner":false,"widgetType":"text-editor","elType":"widget"}],"isInner":true,"elType":"column"}],"isInner":true,"elType":"section"},{"id":"1b5fbdbb","settings":{"css_classes":"press-listing","html_tag":"article","background_background":"classic","border_border":"solid","border_width":{"unit":"px","top":"1","right":"1","bottom":"1","left":"1","isLinked":true},"border_color":"#D5D5D4","padding":{"unit":"em","top":"0.5","right":"0.5","bottom":"0.5","left":"0.5","isLinked":true}},"elements":[{"id":"5da78f5f","settings":{"_column_size":100,"_inline_size":null,"_inline_size_tablet":88,"_inline_size_mobile":80},"elements":[{"id":"74fc98dc","settings":{"title":"Press Article Title","link":{"url":"#","is_external":"on","nofollow":""},"header_size":"h3","typography_font_size":{"unit":"em","size":1.25,"sizes":[]},"eael_tooltip_section_content":"I am a tooltip","eael_ext_content_protection_password_placeholder":"Enter Password","eael_ext_content_protection_password_submit_btn_txt":"Submit"},"elements":[],"isInner":false,"widgetType":"heading","elType":"widget"},{"id":"35b5da48","settings":{"editor":"<p><em>Media Outlet<\/em>, Publication Date<\/p>","typography_font_size":{"unit":"em","size":0.770000000000000017763568394002504646778106689453125,"sizes":[]},"eael_tooltip_section_content":"I am a tooltip","eael_ext_content_protection_password_placeholder":"Enter Password","eael_ext_content_protection_password_submit_btn_txt":"Submit"},"elements":[],"isInner":false,"widgetType":"text-editor","elType":"widget"}],"isInner":true,"elType":"column"}],"isInner":true,"elType":"section"}],"isInner":false,"elType":"column"}],"isInner":false,"elType":"section"}],"page_settings":{"eael_ext_toc_title":"Table of Contents"}}